{
    "scripture": [
        {
            "kaanda": 6,
            "sukta": 17,
            "mantras": 4,
            "rishi": "Atharvaa",
            "devataa": "Garbhadrinhanam",
            "chhanda": "Anushtup",
            "document": "./docs/Atharvaveda06.017.pdf",
            "audio": "",
            "summary": [
                "This composition contains prayers for protection of the fetus and the normal delivery of the child. As Mother Earth holds and nourishes all beings, plants and mountains in its womb, so should a woman hold and nourish her fetus."
            ]
        }
    ]
}